tsururu/__init__.py
tsururu/dataset/__init__.py
tsururu/dataset/dataset.py
tsururu/dataset/pipeline.py
tsururu/dataset/slice.py
tsururu/model_training/__init__.py
tsururu/model_training/torch_based/__init__.py
tsururu/model_training/torch_based/callbacks.py
tsururu/model_training/torch_based/data_provider.py
tsururu/model_training/torch_based/metrics.py
tsururu/model_training/trainer.py
tsururu/model_training/validator.py
tsururu/models/__init__.py
tsururu/models/boost.py
tsururu/models/ml_base.py
tsururu/models/torch_based/__init__.py
tsururu/models/torch_based/cycle_net.py
tsururu/models/torch_based/dl_base.py
tsururu/models/torch_based/dlinear.py
tsururu/models/torch_based/gpt.py
tsururu/models/torch_based/layers/__init__.py
tsururu/models/torch_based/layers/convolution.py
tsururu/models/torch_based/layers/decomposition.py
tsururu/models/torch_based/layers/embedding.py
tsururu/models/torch_based/layers/patch_tst.py
tsururu/models/torch_based/layers/positional_encoding.py
tsururu/models/torch_based/layers/rev_in.py
tsururu/models/torch_based/layers/utils.py
tsururu/models/torch_based/patch_tst.py
tsururu/models/torch_based/times_net.py
tsururu/models/torch_based/utils.py
tsururu/strategies/__init__.py
tsururu/strategies/base.py
tsururu/strategies/direct.py
tsururu/strategies/flat_wide_mimo.py
tsururu/strategies/mimo.py
tsururu/strategies/recursive.py
tsururu/strategies/utils.py
tsururu/transformers/__init__.py
tsururu/transformers/base.py
tsururu/transformers/categorical.py
tsururu/transformers/datetime.py
tsururu/transformers/impute.py
tsururu/transformers/numeric.py
tsururu/transformers/seq.py
tsururu/transformers/utils.py
tsururu/utils/__init__.py
tsururu/utils/logging.py
tsururu/utils/optional_imports.py
tsururu-1.1.0.dist-info/LICENSE
tsururu-1.1.0.dist-info/METADATA
tsururu-1.1.0.dist-info/WHEEL
tsururu-1.1.0.dist-info/RECORD
