Metadata-Version: 2.3
Name: tsururu
Version: 1.1.0
Summary: Python tool for time series forecasting
License: Apache-2.0
Author: Alina Kostromina
Author-email: alina.kostromina@gmail.com
Requires-Python: >=3.9,<3.14
Classifier: Programming Language :: Python :: 3.9
Classifier: Programming Language :: Python :: 3.10
Classifier: Programming Language :: Python :: 3.11
Classifier: Programming Language :: Python :: 3.12
Classifier: Programming Language :: Python :: 3.13
Classifier: Operating System :: OS Independent
Classifier: Intended Audience :: Science/Research
Classifier: Development Status :: 3 - Alpha
Classifier: Environment :: Console
Classifier: Natural Language :: Russian
Classifier: Topic :: Scientific/Engineering :: Artificial Intelligence
Provides-Extra: all
Provides-Extra: catboost
Provides-Extra: pyboost
Provides-Extra: torch
Requires-Dist: catboost (>=1.2.0) ; extra == "all"
Requires-Dist: catboost (>=1.2.0) ; extra == "catboost"
Requires-Dist: einops ; extra == "all"
Requires-Dist: einops ; extra == "torch"
Requires-Dist: holidays (>=0.40,<0.41)
Requires-Dist: numpy (>=1.26.3,<2.0.0)
Requires-Dist: pandas (>=2.2,<3.0)
Requires-Dist: py-boost ; extra == "all"
Requires-Dist: py-boost ; extra == "pyboost"
Requires-Dist: scikit-learn (>=1.3.2,<2.0.0)
Requires-Dist: scipy (>=1.11.4,<2.0.0)
Requires-Dist: torch (>=1.9.0) ; extra == "all"
Requires-Dist: torch (>=1.9.0) ; extra == "torch"
Requires-Dist: transformers ; extra == "all"
Requires-Dist: transformers ; extra == "torch"
Project-URL: Homepage, https://github.com/sb-ai-lab/tsururu
Project-URL: Issues, https://github.com/sb-ai-lab/tsururu/issues
